samplotlib/__init__.py
samplotlib/baseplot.py
samplotlib/circusboy.py
samplotlib/colors.py
samplotlib/graylady.py
samplotlib/utils.py
samplotlib-0.0.6.dist-info/LICENSE.md
samplotlib-0.0.6.dist-info/METADATA
samplotlib-0.0.6.dist-info/WHEEL
samplotlib-0.0.6.dist-info/top_level.txt
samplotlib-0.0.6.dist-info/RECORD
